<!--
theme name:		nesmini
version:		1.0
author:			ruckage
-->
<theme>
	<formatVersion>3</formatVersion>
	<include>./layout.xml</include>
	<include>./${system.theme}/style.xml</include>
	<view name="system">
		<helpsystem name="help">
			<pos>2 2</pos>
			<textColor>f11c00</textColor>
			<iconColor>f11c00</iconColor>
			<fontPath>./art/TinyUnicode.ttf</fontPath>
			<fontSize>0.06666666666666</fontSize>
		</helpsystem>
		<image name="background" extra="true">
			<path>./${system.theme}/system_art.png</path>
			<default>./default/default_art.png</default>
		</image>
		<image name="system_help" extra="true">
			<path>./art/system_help.png</path>
			<pos>0 1</pos>
			<origin>0 1</origin>
		</image>
	</view>
	<feature supported="carousel">
		<view name="system">
			<image name="background" extra="true">
				<path>./${system.theme}/system_art.png</path>
				<default>./default/default_art.png</default>
			</image>
			<carousel name="systemcarousel">
				<type>horizontal</type>
				<color>00000000</color>
				<logoScale>1</logoScale>
			</carousel>
			<image name="logo">
				<path>./${system.theme}/carousel_logo.png</path>
				<default>./default/default_logo.png</default>
			</image>
			<text name="logoText">
				<fontPath>./art/TinyUnicode.ttf</fontPath>
				<color>FF0000</color>
				<forceUppercase>true</forceUppercase>
			</text>
			<text name="systemInfo">
				<backgroundColor>00000000</backgroundColor>
				<color>FFFFFF</color>
				<fontPath>./art/NESCyrillic_gamelist.ttf</fontPath>
				<fontSize>0.0592592592592593</fontSize>
			</text>
			<image name="carousel_bar" extra="false">
				<path>./art/carousel_bar.png</path>
				<origin>0.5 0</origin>
			</image>
		</view>
	</feature>
	<view name="basic, detailed, video">
		<image name="background" extra="true">
			<pos>0 0.5</pos>
			<origin>0 0.5</origin>
			<path>./${system.theme}/menu_background.png</path>
			<default>./default/default_background.png</default>
		</image>
		<image name="gamelist_help" extra="true">
			<path>./art/gamelist_help.png</path>
			<pos>0 1</pos>
			<origin>0 1</origin>
		</image>
		<helpsystem name="help">
			<pos>2 2</pos>
			<textColor>f11c00</textColor>
			<iconColor>f11c00</iconColor>
			<fontPath>./art/TinyUnicode.ttf</fontPath>
			<fontSize>0.06666666666666</fontSize>
		</helpsystem>
		<textlist name="gamelist">
			<forceUppercase>0</forceUppercase>
			<scrollSound>./sounds/se_sys_cursor.wav</scrollSound>
			<fontPath>./art/NESCyrillic_gamelist.ttf</fontPath>
			<alignment>left</alignment>
			<horizontalMargin>0.0083333333333333</horizontalMargin>
			<fontSize>0.038</fontSize>
		</textlist>
		<sound name="systemscroll">
			<path>./sounds/systemscroll.wav</path>
		</sound>
		<sound name="systemselect">
			<path>./sounds/systemselect.wav</path>
		</sound>
		<sound name="back">
			<path>./sounds/back.wav</path>
		</sound>
		<sound name="launch">
			<path>./art/launch.wav</path>
		</sound>
		<sound name="menuopen">
			<path>./sounds/menu.wav</path>
		</sound>
		<sound name="launch">
			<path>./sounds/se_sys_click_game.wav</path>
		</sound>
	</view>
	<view name="basic">
	</view>
	<view name="detailed">
	</view>
</theme>